sumo3Dviz/__init__.py
sumo3Dviz/cli/config_schema.json
sumo3Dviz/cli/render_cli.py
sumo3Dviz/data/sources.txt
sumo3Dviz/data/3d_models/buildings/10065_Corner Grocery Store_V2_Diffuse.jpg
sumo3Dviz/data/3d_models/buildings/10065_Corner Grocery Store_V2_L3.mtl
sumo3Dviz/data/3d_models/buildings/10065_Corner Grocery Store_V2_L3.obj
sumo3Dviz/data/3d_models/buildings/10084_Small Home_V1_Diffuse.jpg
sumo3Dviz/data/3d_models/buildings/10084_Small Home_V3_Iteration0.mtl
sumo3Dviz/data/3d_models/buildings/10084_Small Home_V3_Iteration0.obj
sumo3Dviz/data/3d_models/buildings/AussenWand_C.jpg
sumo3Dviz/data/3d_models/buildings/AussenWand_N.jpg
sumo3Dviz/data/3d_models/buildings/Box_D.jpg
sumo3Dviz/data/3d_models/buildings/Box_N.jpg
sumo3Dviz/data/3d_models/buildings/Grass_col.JPG
sumo3Dviz/data/3d_models/buildings/Hotel_Hous_AO.png
sumo3Dviz/data/3d_models/buildings/REF 1.jpg
sumo3Dviz/data/3d_models/buildings/Reflexion.jpg
sumo3Dviz/data/3d_models/buildings/Residential Buildings 001.mtl
sumo3Dviz/data/3d_models/buildings/Residential Buildings 001.obj
sumo3Dviz/data/3d_models/buildings/Residential Buildings 002.mtl
sumo3Dviz/data/3d_models/buildings/Residential Buildings 002.obj
sumo3Dviz/data/3d_models/buildings/Residential Buildings 003.mtl
sumo3Dviz/data/3d_models/buildings/Residential Buildings 003.obj
sumo3Dviz/data/3d_models/buildings/Residential Buildings 004.mtl
sumo3Dviz/data/3d_models/buildings/Residential Buildings 004.obj
sumo3Dviz/data/3d_models/buildings/Residential Buildings 005.mtl
sumo3Dviz/data/3d_models/buildings/Residential Buildings 005.obj
sumo3Dviz/data/3d_models/buildings/Residential Buildings 006.mtl
sumo3Dviz/data/3d_models/buildings/Residential Buildings 006.obj
sumo3Dviz/data/3d_models/buildings/Residential Buildings 007.mtl
sumo3Dviz/data/3d_models/buildings/Residential Buildings 007.obj
sumo3Dviz/data/3d_models/buildings/Residential Buildings 008.mtl
sumo3Dviz/data/3d_models/buildings/Residential Buildings 008.obj
sumo3dviz-0.1.2.dist-info/licenses/LICENSE
sumo3dviz-0.1.2.dist-info/METADATA
sumo3dviz-0.1.2.dist-info/WHEEL
sumo3dviz-0.1.2.dist-info/top_level.txt
sumo3dviz-0.1.2.dist-info/RECORD
