Metadata-Version: 2.4
Name: sumo3Dviz
Version: 0.1.2
Summary: 3D visualization of SUMO traffic simulations
Author-email: Kevin Riehl <kriehl@ethz.ch>, Julius Schlapbach <juliussc@ethz.ch>
Requires-Python: >=3.9
License-File: LICENSE
Requires-Dist: numpy==1.24.4
Requires-Dist: opencv-python==4.9.0.80
Requires-Dist: pandas==2.1.1
Requires-Dist: panda3d==1.10.15
Requires-Dist: sumolib==1.25.0
Requires-Dist: PyYAML==6.0.3
Requires-Dist: pandera==0.26.1
Requires-Dist: jsonschema==4.25.1
Provides-Extra: dev
Requires-Dist: pytest<9.0.0,>=8.0.0; extra == "dev"
Requires-Dist: pylint<4.0.0,>=3.0.0; extra == "dev"
Requires-Dist: git-cliff<3.0.0,>=2.11.0; extra == "dev"
Dynamic: license-file
